gpt_batch_api/__init__.py
gpt_batch_api/_version.py
gpt_batch_api/gpt_requester.py
gpt_batch_api/logger.py
gpt_batch_api/task_manager.py
gpt_batch_api/task_manager_demo.py
gpt_batch_api/tokens.py
gpt_batch_api/tokens_test.py
gpt_batch_api/utils.py
gpt_batch_api/utils_test.py
gpt_batch_api/wandb_configure_view.py
gpt_batch_api/config/__init__.py
gpt_batch_api/config/gpt_batch_api.yaml
gpt_batch_api-1.0.5.dist-info/licenses/LICENSE
gpt_batch_api-1.0.5.dist-info/METADATA
gpt_batch_api-1.0.5.dist-info/WHEEL
gpt_batch_api-1.0.5.dist-info/top_level.txt
gpt_batch_api-1.0.5.dist-info/RECORD
