Metadata-Version: 2.4
Name: gpt_batch_api
Version: 1.0.5
Summary: Efficiently and robustly use the OpenAI Batch API in Python
Author: Philipp Allgeuer
Maintainer: Philipp Allgeuer
License-Expression: GPL-3.0-or-later
Project-URL: Homepage, https://github.com/pallgeuer/gpt_batch_api
Project-URL: Source Code, https://github.com/pallgeuer/gpt_batch_api
Project-URL: Issue Tracker, https://github.com/pallgeuer/gpt_batch_api/issues
Keywords: OpenAI,ChatGPT,Batch API,LLM,NLP,Python
Classifier: Development Status :: 5 - Production/Stable
Classifier: Intended Audience :: Developers
Classifier: Intended Audience :: Science/Research
Classifier: Operating System :: OS Independent
Classifier: Programming Language :: Python :: 3
Classifier: Programming Language :: Python :: 3.12
Classifier: Topic :: Software Development :: Libraries
Classifier: Topic :: Scientific/Engineering :: Artificial Intelligence
Requires-Python: >=3.12
License-File: LICENSE
Requires-Dist: filelock
Requires-Dist: openai
Requires-Dist: pillow
Requires-Dist: pydantic>=2
Requires-Dist: requests
Requires-Dist: tiktoken
Requires-Dist: wandb
Requires-Dist: wandb-workspaces
Provides-Extra: dev
Requires-Dist: pytest; extra == "dev"
Dynamic: license-file
